{
  "tracks": [
    {
      "Index": 1,
      "Ctgr": "DM",
      "Name": "Angelic Sphere",
      "Cmps": "3R2"
    },
    {
      "Index": 2,
      "Ctgr": "P2",
      "Name": "Bye Bye Love",
      "Cmps": "3rd Coast"
    },
    {
      "Index": 3,
      "Ctgr": "CE",
      "Name": "Closer",
      "Cmps": "3rd Coast"
    },
    {
      "Index": 4,
      "Ctgr": "CE",
      "Name": "Coastal Tempo",
      "Cmps": "3rd Coast"
    },
    {
      "Index": 5,
      "Ctgr": "P3",
      "Name": "Everything",
      "Cmps": "3rd Coast"
    },
    {
      "Index": 6,
      "Ctgr": "T3",
      "Name": "Fallin' in LUV",
      "Cmps": "3rd Coast"
    },
    {
      "Index": 7,
      "Ctgr": "BS",
      "Name": "Jealousy",
      "Cmps": "3rd Coast"
    },
    {
      "Index": 8,
      "Ctgr": "P1",
      "Name": "Let's Go Baby",
      "Cmps": "3rd Coast"
    },
    {
      "Index": 9,
      "Ctgr": "P1",
      "Name": "Luv Flow",
      "Cmps": "3rd Coast"
    },
    {
      "Index": 10,
      "Ctgr": "P3",
      "Name": "Luv is True",
      "Cmps": "3rd Coast"
    },
    {
      "Index": 11,
      "Ctgr": "T3",
      "Name": "My Heart, My Soul",
      "Cmps": "3rd Coast"
    },
    {
      "Index": 12,
      "Ctgr": "TR",
      "Name": "My Jealousy",
      "Cmps": "3rd Coast"
    },
    {
      "Index": 13,
      "Ctgr": "P2",
      "Name": "sO mUCH iN LUV",
      "Cmps": "3rd Coast"
    },
    {
      "Index": 14,
      "Ctgr": "TR",
      "Name": "STOP",
      "Cmps": "3rd Coast"
    },
    {
      "Index": 15,
      "Ctgr": "T1",
      "Name": "Beyond the Future",
      "Cmps": "7 Sequence"
    },
    {
      "Index": 16,
      "Ctgr": "BS",
      "Name": "Cypher Gate",
      "Cmps": "7 Sequence"
    },
    {
      "Index": 17,
      "Ctgr": "T2",
      "Name": "Dual Strikers",
      "Cmps": "7 Sequence"
    },
    {
      "Index": 18,
      "Ctgr": "RE",
      "Name": "Get Jinxed",
      "Cmps": "Agnete K"
    },
    {
      "Index": 19,
      "Ctgr": "RE",
      "Name": "End of Mythology",
      "Cmps": "Alice Schach and the Magic Orchestra"
    },
    {
      "Index": 20,
      "Ctgr": "VE",
      "Name": "Maharajah -fenomeno edition-",
      "Cmps": "Alice Schach and the Magic Orchestra"
    },
    {
      "Index": 21,
      "Ctgr": "RE",
      "Name": "염라",
      "Cmps": "ampstyle"
    },
    {
      "Index": 22,
      "Ctgr": "RE",
      "Name": "너로피어오라",
      "Cmps": "ampstyle"
    },
    {
      "Index": 23,
      "Ctgr": "T3",
      "Name": "Kung-Fu Rider",
      "Cmps": "AstroKid"
    },
    {
      "Index": 24,
      "Ctgr": "RE",
      "Name": "Bleed",
      "Cmps": "Axol & The Tech Thieves"
    },
    {
      "Index": 25,
      "Ctgr": "GF",
      "Name": "Frontline",
      "Cmps": "B@kamin / M2U"
    },
    {
      "Index": 26,
      "Ctgr": "VE",
      "Name": "Space Challenger",
      "Cmps": "Bagagee Viphex13"
    },
    {
      "Index": 27,
      "Ctgr": "VE",
      "Name": "Lost Serenity",
      "Cmps": "Benicx"
    },
    {
      "Index": 28,
      "Ctgr": "T2",
      "Name": "Cozy Quilt",
      "Cmps": "bermei.inazawa"
    },
    {
      "Index": 29,
      "Ctgr": "P2",
      "Name": "Lost n' found",
      "Cmps": "bermei.inazawa"
    },
    {
      "Index": 30,
      "Ctgr": "T1",
      "Name": "Melody",
      "Cmps": "bermei.inazawa"
    },
    {
      "Index": 31,
      "Ctgr": "RE",
      "Name": "quixotic",
      "Cmps": "bermei.inazawa"
    },
    {
      "Index": 32,
      "Ctgr": "RE",
      "Name": "Royal Clown",
      "Cmps": "bermei.inazawa"
    },
    {
      "Index": 33,
      "Ctgr": "RE",
      "Name": "BlackCat",
      "Cmps": "BEXTER"
    },
    {
      "Index": 34,
      "Ctgr": "RE",
      "Name": "Boom!",
      "Cmps": "BEXTER"
    },
    {
      "Index": 35,
      "Ctgr": "P2",
      "Name": "Brave it Out",
      "Cmps": "BEXTER"
    },
    {
      "Index": 36,
      "Ctgr": "VE",
      "Name": "Dream it",
      "Cmps": "BEXTER"
    },
    {
      "Index": 37,
      "Ctgr": "BS",
      "Name": "Ruti'n",
      "Cmps": "BEXTER"
    },
    {
      "Index": 38,
      "Ctgr": "P2",
      "Name": "Syriana",
      "Cmps": "BEXTER"
    },
    {
      "Index": 39,
      "Ctgr": "TR",
      "Name": "Yo Creo Que Si ~Live House Version~",
      "Cmps": "BEXTER"
    },
    {
      "Index": 40,
      "Ctgr": "TR",
      "Name": "ZET",
      "Cmps": "BEXTER"
    },
    {
      "Index": 41,
      "Ctgr": "CE",
      "Name": "영원",
      "Cmps": "BEXTER"
    },
    {
      "Index": 42,
      "Ctgr": "RE",
      "Name": "glory day",
      "Cmps": "BEXTER x Mycin.T"
    },
    {
      "Index": 43,
      "Ctgr": "CE",
      "Name": "First Kiss",
      "Cmps": "BJJ"
    },
    {
      "Index": 44,
      "Ctgr": "BS",
      "Name": "Get Down",
      "Cmps": "BJJ"
    },
    {
      "Index": 45,
      "Ctgr": "P3",
      "Name": "Your Smile",
      "Cmps": "Cistrans (RoseLine)"
    },
    {
      "Index": 46,
      "Ctgr": "CE",
      "Name": "Color",
      "Cmps": "CLAZZIQUAI"
    },
    {
      "Index": 47,
      "Ctgr": "CE",
      "Name": "Creator",
      "Cmps": "CLAZZIQUAI"
    },
    {
      "Index": 48,
      "Ctgr": "CE",
      "Name": "Electronics",
      "Cmps": "CLAZZIQUAI"
    },
    {
      "Index": 49,
      "Ctgr": "CE",
      "Name": "Flea",
      "Cmps": "CLAZZIQUAI"
    },
    {
      "Index": 50,
      "Ctgr": "CE",
      "Name": "Freedom",
      "Cmps": "CLAZZIQUAI"
    },
    {
      "Index": 51,
      "Ctgr": "CE",
      "Name": "Love Mode",
      "Cmps": "CLAZZIQUAI"
    },
    {
      "Index": 52,
      "Ctgr": "CE",
      "Name": "The Night Stage",
      "Cmps": "CLAZZIQUAI"
    },
    {
      "Index": 53,
      "Ctgr": "CE",
      "Name": "내게로 와",
      "Cmps": "CLAZZIQUAI"
    },
    {
      "Index": 54,
      "Ctgr": "GC",
      "Name": "Black MInD",
      "Cmps": "COSIO"
    },
    {
      "Index": 55,
      "Ctgr": "GC",
      "Name": "Groove Prayer",
      "Cmps": "COSIO"
    },
    {
      "Index": 56,
      "Ctgr": "VE",
      "Name": "BLACK GOLD",
      "Cmps": "Cranky"
    },
    {
      "Index": 57,
      "Ctgr": "T2",
      "Name": "La Campanella ： Nu Rave",
      "Cmps": "Cranky"
    },
    {
      "Index": 58,
      "Ctgr": "CY",
      "Name": "Old Gold",
      "Cmps": "Cranky"
    },
    {
      "Index": 59,
      "Ctgr": "T3",
      "Name": "Supernova",
      "Cmps": "Cranky"
    },
    {
      "Index": 60,
      "Ctgr": "GC",
      "Name": "Warrior",
      "Cmps": "Cranky"
    },
    {
      "Index": 61,
      "Ctgr": "CY",
      "Name": "conflict",
      "Cmps": "Cranky + siromaru"
    },
    {
      "Index": 62,
      "Ctgr": "GC",
      "Name": "ouroboros -twin stroke of the end-",
      "Cmps": "Cranky vs MASAKI"
    },
    {
      "Index": 63,
      "Ctgr": "P1",
      "Name": "CnP",
      "Cmps": "CRooFE"
    },
    {
      "Index": 64,
      "Ctgr": "T3",
      "Name": "AD2222",
      "Cmps": "Croove"
    },
    {
      "Index": 65,
      "Ctgr": "T3",
      "Name": "AD2222 ~Extended Mix~",
      "Cmps": "Croove"
    },
    {
      "Index": 66,
      "Ctgr": "P2",
      "Name": "Brain Storm",
      "Cmps": "Croove"
    },
    {
      "Index": 67,
      "Ctgr": "BS",
      "Name": "Desperado",
      "Cmps": "Croove"
    },
    {
      "Index": 68,
      "Ctgr": "P1",
      "Name": "Enemy Storm",
      "Cmps": "Croove"
    },
    {
      "Index": 69,
      "Ctgr": "P1",
      "Name": "JBG",
      "Cmps": "Croove"
    },
    {
      "Index": 70,
      "Ctgr": "P1",
      "Name": "MASAI",
      "Cmps": "Croove"
    },
    {
      "Index": 71,
      "Ctgr": "P2",
      "Name": "Minus 3",
      "Cmps": "Croove"
    },
    {
      "Index": 72,
      "Ctgr": "P1",
      "Name": "Out Law",
      "Cmps": "Croove"
    },
    {
      "Index": 73,
      "Ctgr": "P1",
      "Name": "RED",
      "Cmps": "Croove"
    },
    {
      "Index": 74,
      "Ctgr": "P1",
      "Name": "Sunny Side",
      "Cmps": "Croove"
    },
    {
      "Index": 75,
      "Ctgr": "T1",
      "Name": "Sweet Shining Shooting Star",
      "Cmps": "Croove"
    },
    {
      "Index": 76,
      "Ctgr": "RE",
      "Name": "waiting for me",
      "Cmps": "Croove"
    },
    {
      "Index": 77,
      "Ctgr": "RE",
      "Name": "v o l d e n u i t",
      "Cmps": "Cuve"
    },
    {
      "Index": 78,
      "Ctgr": "TR",
      "Name": "Ventilator",
      "Cmps": "Cycle75"
    },
    {
      "Index": 79,
      "Ctgr": "GG",
      "Name": "Break a Spell",
      "Cmps": "Daisuke Ishiwatari"
    },
    {
      "Index": 80,
      "Ctgr": "GG",
      "Name": "Holy Orders (Be Just Or Be Dead)",
      "Cmps": "Daisuke Ishiwatari"
    },
    {
      "Index": 81,
      "Ctgr": "GG",
      "Name": "Marionette",
      "Cmps": "Daisuke Ishiwatari"
    },
    {
      "Index": 82,
      "Ctgr": "P2",
      "Name": "My Alias",
      "Cmps": "Dayz"
    },
    {
      "Index": 83,
      "Ctgr": "P2",
      "Name": "NANO RISK",
      "Cmps": "Dayz"
    },
    {
      "Index": 84,
      "Ctgr": "RE",
      "Name": "Rising The Sonic",
      "Cmps": "Dayz"
    },
    {
      "Index": 85,
      "Ctgr": "T2",
      "Name": "Cosmic Fantastic Lovesong",
      "Cmps": "DINY"
    },
    {
      "Index": 86,
      "Ctgr": "T3",
      "Name": "Dream Again",
      "Cmps": "DINY"
    },
    {
      "Index": 87,
      "Ctgr": "RE",
      "Name": "Secret Dejavu",
      "Cmps": "DINY"
    },
    {
      "Index": 88,
      "Ctgr": "P2",
      "Name": "Fallen Angel",
      "Cmps": "DJ Mocha"
    },
    {
      "Index": 89,
      "Ctgr": "ES",
      "Name": "Feel",
      "Cmps": "DJ Mocha"
    },
    {
      "Index": 90,
      "Ctgr": "TR",
      "Name": "GET OUT ~Hip Noodle Mix~",
      "Cmps": "DJ.EON"
    },
    {
      "Index": 91,
      "Ctgr": "TR",
      "Name": "Syriana ~Blast Wave Mix~",
      "Cmps": "DJ.EON"
    },
    {
      "Index": 92,
      "Ctgr": "GC",
      "Name": "Got more raves？",
      "Cmps": "E.G.G."
    },
    {
      "Index": 93,
      "Ctgr": "P1",
      "Name": "Dreadnought",
      "Cmps": "EarBreaker"
    },
    {
      "Index": 94,
      "Ctgr": "P1",
      "Name": "Minimal Life",
      "Cmps": "EarBreaker"
    },
    {
      "Index": 95,
      "Ctgr": "ES",
      "Name": "Super lovely",
      "Cmps": "EarBreaker"
    },
    {
      "Index": 96,
      "Ctgr": "P2",
      "Name": "Fentanest",
      "Cmps": "EarBreaker & Eszett"
    },
    {
      "Index": 97,
      "Ctgr": "TR",
      "Name": "A Lie ~Deep Inside Mix~",
      "Cmps": "Electronic Boutique"
    },
    {
      "Index": 98,
      "Ctgr": "TR",
      "Name": "Bye Bye Love ~Nu Jazz Mix~",
      "Cmps": "Electronic Boutique"
    },
    {
      "Index": 99,
      "Ctgr": "P2",
      "Name": "DIVINE SERVICE",
      "Cmps": "Electronic Boutique"
    },
    {
      "Index": 100,
      "Ctgr": "T1",
      "Name": "HEXAD",
      "Cmps": "Electronic Boutique"
    },
    {
      "Index": 101,
      "Ctgr": "T2",
      "Name": "Love is Beautiful",
      "Cmps": "Electronic Boutique"
    },
    {
      "Index": 102,
      "Ctgr": "P2",
      "Name": "Miles",
      "Cmps": "Electronic Boutique"
    },
    {
      "Index": 103,
      "Ctgr": "P2",
      "Name": "Negative Nature",
      "Cmps": "Electronic Boutique"
    },
    {
      "Index": 104,
      "Ctgr": "T2",
      "Name": "Puzzler",
      "Cmps": "Electronic Boutique"
    },
    {
      "Index": 105,
      "Ctgr": "CE",
      "Name": "Urban Night (hYO)",
      "Cmps": "hYO"
    },
    {
      "Index": 106,
      "Ctgr": "ES",
      "Name": "Urban Night (Electronic Boutique)",
      "Cmps": "Electronic Boutique"
    },
    {
      "Index": 107,
      "Ctgr": "EM",
      "Name": "HELIX",
      "Cmps": "ESTi"
    },
    {
      "Index": 108,
      "Ctgr": "EM",
      "Name": "In My Heart ~ESTi Remix~",
      "Cmps": "ESTi"
    },
    {
      "Index": 109,
      "Ctgr": "P2",
      "Name": "Ladymade Star",
      "Cmps": "ESTi"
    },
    {
      "Index": 110,
      "Ctgr": "P1",
      "Name": "Long Vacation",
      "Cmps": "ESTi"
    },
    {
      "Index": 111,
      "Ctgr": "P1",
      "Name": "OBLIVION",
      "Cmps": "ESTi"
    },
    {
      "Index": 112,
      "Ctgr": "P1",
      "Name": "Ray of Illuminati",
      "Cmps": "ESTi"
    },
    {
      "Index": 113,
      "Ctgr": "P1",
      "Name": "SIN",
      "Cmps": "ESTi"
    },
    {
      "Index": 114,
      "Ctgr": "P1",
      "Name": "SIN ~The Last Scene~",
      "Cmps": "ESTi"
    },
    {
      "Index": 115,
      "Ctgr": "EM",
      "Name": "U-NIVUS",
      "Cmps": "ESTi"
    },
    {
      "Index": 116,
      "Ctgr": "RE",
      "Name": "서울여자",
      "Cmps": "ESTi"
    },
    {
      "Index": 117,
      "Ctgr": "EM",
      "Name": "Obelisque",
      "Cmps": "ESTi & M2U"
    },
    {
      "Index": 118,
      "Ctgr": "T2",
      "Name": "BEE-U-TIFUL",
      "Cmps": "First Aid"
    },
    {
      "Index": 119,
      "Ctgr": "T2",
      "Name": "D2",
      "Cmps": "First Aid"
    },
    {
      "Index": 120,
      "Ctgr": "P1",
      "Name": "A.I",
      "Cmps": "Forte Escape"
    },
    {
      "Index": 121,
      "Ctgr": "P2",
      "Name": "Another DAY",
      "Cmps": "Forte Escape"
    },
    {
      "Index": 122,
      "Ctgr": "P1",
      "Name": "Astro Fight",
      "Cmps": "Forte Escape"
    },
    {
      "Index": 123,
      "Ctgr": "P1",
      "Name": "Can We Talk",
      "Cmps": "Forte Escape"
    },
    {
      "Index": 124,
      "Ctgr": "P1",
      "Name": "Catch Me",
      "Cmps": "Forte Escape"
    },
    {
      "Index": 125,
      "Ctgr": "TR",
      "Name": "Catch You",
      "Cmps": "Forte Escape"
    },
    {
      "Index": 126,
      "Ctgr": "ES",
      "Name": "Cosmic Elevator",
      "Cmps": "Forte Escape"
    },
    {
      "Index": 127,
      "Ctgr": "P1",
      "Name": "Elastic STAR",
      "Cmps": "Forte Escape"
    },
    {
      "Index": 128,
      "Ctgr": "P1",
      "Name": "End of the Moonlight",
      "Cmps": "Forte Escape"
    },
    {
      "Index": 129,
      "Ctgr": "P1",
      "Name": "Extreme Z4",
      "Cmps": "Forte Escape"
    },
    {
      "Index": 130,
      "Ctgr": "P1",
      "Name": "Funky Chups",
      "Cmps": "Forte Escape"
    },
    {
      "Index": 131,
      "Ctgr": "P1",
      "Name": "Futurism",
      "Cmps": "Forte Escape"
    },
    {
      "Index": 132,
      "Ctgr": "ES",
      "Name": "Knowledge System",
      "Cmps": "Forte Escape"
    },
    {
      "Index": 133,
      "Ctgr": "P1",
      "Name": "Para-Q",
      "Cmps": "Forte Escape"
    },
    {
      "Index": 134,
      "Ctgr": "P1",
      "Name": "Save My Dream",
      "Cmps": "Forte Escape"
    },
    {
      "Index": 135,
      "Ctgr": "TR",
      "Name": "sO mUCH iN LUV ~Melodic Twisted Mix~",
      "Cmps": "Forte Escape"
    },
    {
      "Index": 136,
      "Ctgr": "P1",
      "Name": "Triple Zoe",
      "Cmps": "Forte Escape"
    },
    {
      "Index": 137,
      "Ctgr": "P1",
      "Name": "Ya! Party!",
      "Cmps": "Forte Escape"
    },
    {
      "Index": 138,
      "Ctgr": "P2",
      "Name": "Yellowberry -AJ Mix-",
      "Cmps": "Forte Escape"
    },
    {
      "Index": 139,
      "Ctgr": "P1",
      "Name": "바람에게 부탁해",
      "Cmps": "Forte Escape"
    },
    {
      "Index": 140,
      "Ctgr": "P1",
      "Name": "바람에게 부탁해 ~Live Mix~",
      "Cmps": "Forte Escape"
    },
    {
      "Index": 141,
      "Ctgr": "TR",
      "Name": "바람의 기억",
      "Cmps": "Forte Escape"
    },
    {
      "Index": 142,
      "Ctgr": "P1",
      "Name": "KUDA",
      "Cmps": "Gonzo"
    },
    {
      "Index": 143,
      "Ctgr": "RE",
      "Name": "Child of Night",
      "Cmps": "GOTH"
    },
    {
      "Index": 144,
      "Ctgr": "RE",
      "Name": "Dance of the Dead",
      "Cmps": "GOTH"
    },
    {
      "Index": 145,
      "Ctgr": "RE",
      "Name": "Enter The Universe",
      "Cmps": "GOTH"
    },
    {
      "Index": 146,
      "Ctgr": "RE",
      "Name": "KILLER BEE",
      "Cmps": "GOTH"
    },
    {
      "Index": 147,
      "Ctgr": "RE",
      "Name": "Ruti'n (GOTH Wild Electro Remix)",
      "Cmps": "GOTH"
    },
    {
      "Index": 148,
      "Ctgr": "RE",
      "Name": "The Obliterator",
      "Cmps": "GOTH"
    },
    {
      "Index": 149,
      "Ctgr": "VE",
      "Name": "Vile Requiem",
      "Cmps": "GOTH"
    },
    {
      "Index": 150,
      "Ctgr": "GF",
      "Name": "What am I fighting for？",
      "Cmps": "Haloweak"
    },
    {
      "Index": 151,
      "Ctgr": "RE",
      "Name": "ANALYS",
      "Cmps": "HAYAKO"
    },
    {
      "Index": 152,
      "Ctgr": "VE",
      "Name": "NANAIRO",
      "Cmps": "HAYAKO"
    },
    {
      "Index": 153,
      "Ctgr": "RE",
      "Name": "U.A.D",
      "Cmps": "HAYAKO"
    },
    {
      "Index": 154,
      "Ctgr": "T1",
      "Name": "SON OF SUN",
      "Cmps": "Hosoe Shinji"
    },
    {
      "Index": 155,
      "Ctgr": "T1",
      "Name": "SON OF SUN ~Extended Mix~",
      "Cmps": "Hosoe Shinji"
    },
    {
      "Index": 156,
      "Ctgr": "T2",
      "Name": "XLASHER",
      "Cmps": "Hosoe Shinji"
    },
    {
      "Index": 157,
      "Ctgr": "VE",
      "Name": "Do it",
      "Cmps": "House Rulez"
    },
    {
      "Index": 158,
      "Ctgr": "RE",
      "Name": "Do you want it",
      "Cmps": "House Rulez"
    },
    {
      "Index": 159,
      "Ctgr": "T1",
      "Name": "DJMAX",
      "Cmps": "Humming Urban Stereo"
    },
    {
      "Index": 160,
      "Ctgr": "T1",
      "Name": "Honeymoon",
      "Cmps": "Humming Urban Stereo"
    },
    {
      "Index": 161,
      "Ctgr": "CY",
      "Name": "Entrance",
      "Cmps": "Ice"
    },
    {
      "Index": 162,
      "Ctgr": "CY",
      "Name": "L",
      "Cmps": "Ice"
    },
    {
      "Index": 163,
      "Ctgr": "VE",
      "Name": "Lost Temple",
      "Cmps": "IMLAY"
    },
    {
      "Index": 164,
      "Ctgr": "VE",
      "Name": "Move Yourself",
      "Cmps": "IMLAY / YESEO"
    },
    {
      "Index": 165,
      "Ctgr": "RE",
      "Name": "OPEN FIRE",
      "Cmps": "JC"
    },
    {
      "Index": 166,
      "Ctgr": "RE",
      "Name": "glory day -JHS Remix-",
      "Cmps": "JHS"
    },
    {
      "Index": 167,
      "Ctgr": "RE",
      "Name": "POP／STARS",
      "Cmps": "K/DA"
    },
    {
      "Index": 168,
      "Ctgr": "P3",
      "Name": "Become Myself",
      "Cmps": "Kibum / Yohan"
    },
    {
      "Index": 169,
      "Ctgr": "RE",
      "Name": "Void",
      "Cmps": "Kobayashi Tetsuya"
    },
    {
      "Index": 170,
      "Ctgr": "T3",
      "Name": "Angel",
      "Cmps": "Laurent Newfield & Ravenant"
    },
    {
      "Index": 171,
      "Ctgr": "T3",
      "Name": "Wanna Be Your Lover",
      "Cmps": "Laurent Newfield & Ravenant"
    },
    {
      "Index": 172,
      "Ctgr": "RE",
      "Name": "Runaway",
      "Cmps": "LeeZu"
    },
    {
      "Index": 173,
      "Ctgr": "T3",
      "Name": "Showdown",
      "Cmps": "LeeZu"
    },
    {
      "Index": 174,
      "Ctgr": "T1",
      "Name": "I want You",
      "Cmps": "Lin-G"
    },
    {
      "Index": 175,
      "Ctgr": "T1",
      "Name": "Remember",
      "Cmps": "Lin-G"
    },
    {
      "Index": 176,
      "Ctgr": "T2",
      "Name": "Sweet Dream",
      "Cmps": "Lin-G"
    },
    {
      "Index": 177,
      "Ctgr": "P1",
      "Name": "BlythE",
      "Cmps": "M2U"
    },
    {
      "Index": 178,
      "Ctgr": "P1",
      "Name": "Bright Dream",
      "Cmps": "M2U"
    },
    {
      "Index": 179,
      "Ctgr": "P1",
      "Name": "Eternal Memory ~소녀의 꿈~",
      "Cmps": "M2U"
    },
    {
      "Index": 180,
      "Ctgr": "P1",
      "Name": "Lemonade",
      "Cmps": "M2U"
    },
    {
      "Index": 181,
      "Ctgr": "DM",
      "Name": "Magnolia",
      "Cmps": "M2U"
    },
    {
      "Index": 182,
      "Ctgr": "P2",
      "Name": "Memoirs",
      "Cmps": "M2U"
    },
    {
      "Index": 183,
      "Ctgr": "P1",
      "Name": "Memory of Beach",
      "Cmps": "M2U"
    },
    {
      "Index": 184,
      "Ctgr": "CY",
      "Name": "Myosotis",
      "Cmps": "M2U"
    },
    {
      "Index": 185,
      "Ctgr": "P1",
      "Name": "NB RANGER",
      "Cmps": "M2U"
    },
    {
      "Index": 186,
      "Ctgr": "P2",
      "Name": "Nightmare",
      "Cmps": "M2U"
    },
    {
      "Index": 187,
      "Ctgr": "P2",
      "Name": "Phantom Of Sky",
      "Cmps": "M2U"
    },
    {
      "Index": 188,
      "Ctgr": "P2",
      "Name": "Seeker",
      "Cmps": "M2U"
    },
    {
      "Index": 189,
      "Ctgr": "ES",
      "Name": "Space of Soul",
      "Cmps": "M2U"
    },
    {
      "Index": 190,
      "Ctgr": "P2",
      "Name": "A Lie",
      "Cmps": "makou"
    },
    {
      "Index": 191,
      "Ctgr": "T3",
      "Name": "A Life With You",
      "Cmps": "makou"
    },
    {
      "Index": 192,
      "Ctgr": "BS",
      "Name": "Beat U Down",
      "Cmps": "makou"
    },
    {
      "Index": 193,
      "Ctgr": "P2",
      "Name": "Dream of You",
      "Cmps": "makou"
    },
    {
      "Index": 194,
      "Ctgr": "T3",
      "Name": "Emblem",
      "Cmps": "makou"
    },
    {
      "Index": 195,
      "Ctgr": "BS",
      "Name": "Fermion",
      "Cmps": "makou"
    },
    {
      "Index": 196,
      "Ctgr": "P2",
      "Name": "For Seasons",
      "Cmps": "makou"
    },
    {
      "Index": 197,
      "Ctgr": "P3",
      "Name": "Gone Astray",
      "Cmps": "makou"
    },
    {
      "Index": 198,
      "Ctgr": "P1",
      "Name": "HAMSIN",
      "Cmps": "makou"
    },
    {
      "Index": 199,
      "Ctgr": "RE",
      "Name": "Heavenly",
      "Cmps": "makou"
    },
    {
      "Index": 200,
      "Ctgr": "RE",
      "Name": "Lift You Up",
      "Cmps": "makou"
    },
    {
      "Index": 201,
      "Ctgr": "T2",
      "Name": "Put'Em Up",
      "Cmps": "makou"
    },
    {
      "Index": 202,
      "Ctgr": "P2",
      "Name": "Right Now",
      "Cmps": "makou"
    },
    {
      "Index": 203,
      "Ctgr": "P2",
      "Name": "Rocka-a-doodle-doo",
      "Cmps": "makou"
    },
    {
      "Index": 204,
      "Ctgr": "T2",
      "Name": "Say it from your heart",
      "Cmps": "makou"
    },
    {
      "Index": 205,
      "Ctgr": "P3",
      "Name": "Season (Warm Mix)",
      "Cmps": "makou"
    },
    {
      "Index": 206,
      "Ctgr": "P2",
      "Name": "Smoky Quartz",
      "Cmps": "makou"
    },
    {
      "Index": 207,
      "Ctgr": "P1",
      "Name": "Sunny Side ~Deepn' Soul Mix~",
      "Cmps": "makou"
    },
    {
      "Index": 208,
      "Ctgr": "T1",
      "Name": "Voyage",
      "Cmps": "makou"
    },
    {
      "Index": 209,
      "Ctgr": "P2",
      "Name": "Yo Creo Que Si",
      "Cmps": "makou"
    },
    {
      "Index": 210,
      "Ctgr": "TR",
      "Name": "Your Own Miracle ~Disco House Mix~",
      "Cmps": "makou"
    },
    {
      "Index": 211,
      "Ctgr": "RE",
      "Name": "Alone",
      "Cmps": "Marshmello"
    },
    {
      "Index": 212,
      "Ctgr": "VE",
      "Name": "FIGHT NIGHT (feat. Calyae)",
      "Cmps": "Messier"
    },
    {
      "Index": 213,
      "Ctgr": "DM",
      "Name": "Nine point eight",
      "Cmps": "Mili"
    },
    {
      "Index": 214,
      "Ctgr": "DM",
      "Name": "Utopiosphere",
      "Cmps": "Mili"
    },
    {
      "Index": 215,
      "Ctgr": "DM",
      "Name": "YUBIKIRI-GENMAN",
      "Cmps": "Mili"
    },
    {
      "Index": 216,
      "Ctgr": "P3",
      "Name": "Waiting for the Sun",
      "Cmps": "MindCube"
    },
    {
      "Index": 217,
      "Ctgr": "RE",
      "Name": "glory day (Mintorment Remix)",
      "Cmps": "Mintorment"
    },
    {
      "Index": 218,
      "Ctgr": "VE",
      "Name": "Attack",
      "Cmps": "Mr.Funky"
    },
    {
      "Index": 219,
      "Ctgr": "P3",
      "Name": "Break!",
      "Cmps": "Mr.Funky"
    },
    {
      "Index": 220,
      "Ctgr": "P3",
      "Name": "Hanz up!",
      "Cmps": "Mr.Funky"
    },
    {
      "Index": 221,
      "Ctgr": "T2",
      "Name": "Nova ~Mr.Funky Remix~",
      "Cmps": "Mr.Funky"
    },
    {
      "Index": 222,
      "Ctgr": "P3",
      "Name": "Out Law ： Reborn",
      "Cmps": "Mr.Funky"
    },
    {
      "Index": 223,
      "Ctgr": "T3",
      "Name": "Out of CTRL",
      "Cmps": "Mr.Funky"
    },
    {
      "Index": 224,
      "Ctgr": "RE",
      "Name": "RockSTAR",
      "Cmps": "Mr.Funky"
    },
    {
      "Index": 225,
      "Ctgr": "P3",
      "Name": "Supersonic ~Mr.Funky Dirty Planet Remix~",
      "Cmps": "Mr.Funky"
    },
    {
      "Index": 226,
      "Ctgr": "P3",
      "Name": "ZET ~Mr.Funky Remix~",
      "Cmps": "Mr.Funky"
    },
    {
      "Index": 227,
      "Ctgr": "RE",
      "Name": "Beyond Yourself",
      "Cmps": "Mycin.T"
    },
    {
      "Index": 228,
      "Ctgr": "RE",
      "Name": "Bullet, Wanted!",
      "Cmps": "Mycin.T"
    },
    {
      "Index": 229,
      "Ctgr": "RE",
      "Name": "Groovin Up",
      "Cmps": "Mycin.T"
    },
    {
      "Index": 230,
      "Ctgr": "RE",
      "Name": "Running girl",
      "Cmps": "Mycin.T"
    },
    {
      "Index": 231,
      "Ctgr": "RE",
      "Name": "Waiting for you",
      "Cmps": "Mycin.T"
    },
    {
      "Index": 232,
      "Ctgr": "RE",
      "Name": "비상 ~Stay With Me~",
      "Cmps": "Mycin.T"
    },
    {
      "Index": 233,
      "Ctgr": "RE",
      "Name": "혜성",
      "Cmps": "Mycin.T"
    },
    {
      "Index": 234,
      "Ctgr": "RE",
      "Name": "I want You ~반짝반짝 Sunshine~",
      "Cmps": "Mycin.T x GOTH x jam-jam"
    },
    {
      "Index": 235,
      "Ctgr": "VE",
      "Name": "Misty Er'A",
      "Cmps": "Mycin.T × jam-jam"
    },
    {
      "Index": 236,
      "Ctgr": "VE",
      "Name": "WONDER $LOT 777",
      "Cmps": "MYUKKE."
    },
    {
      "Index": 237,
      "Ctgr": "CY",
      "Name": "Les Parfums de L'Amour",
      "Cmps": "naotyu-"
    },
    {
      "Index": 238,
      "Ctgr": "T3",
      "Name": "EGG",
      "Cmps": "Nauts"
    },
    {
      "Index": 239,
      "Ctgr": "T3",
      "Name": "EGG ~Extended Mix~",
      "Cmps": "Nauts"
    },
    {
      "Index": 240,
      "Ctgr": "RE",
      "Name": "Far East Princess",
      "Cmps": "Nauts"
    },
    {
      "Index": 241,
      "Ctgr": "P2",
      "Name": "Mess it Up",
      "Cmps": "Nauts"
    },
    {
      "Index": 242,
      "Ctgr": "TR",
      "Name": "Streetlight",
      "Cmps": "Nauts"
    },
    {
      "Index": 243,
      "Ctgr": "P2",
      "Name": "Sunset Rider",
      "Cmps": "Nauts"
    },
    {
      "Index": 244,
      "Ctgr": "RE",
      "Name": "WHY",
      "Cmps": "Nauts"
    },
    {
      "Index": 245,
      "Ctgr": "CH",
      "Name": "Ray Tuning",
      "Cmps": "NayutalieN"
    },
    {
      "Index": 246,
      "Ctgr": "RE",
      "Name": "2Nite",
      "Cmps": "ND Lee"
    },
    {
      "Index": 247,
      "Ctgr": "RE",
      "Name": "Beautiful Day",
      "Cmps": "ND Lee"
    },
    {
      "Index": 248,
      "Ctgr": "P2",
      "Name": "GET OUT",
      "Cmps": "ND Lee"
    },
    {
      "Index": 249,
      "Ctgr": "T3",
      "Name": "Give Me 5",
      "Cmps": "ND Lee"
    },
    {
      "Index": 250,
      "Ctgr": "BS",
      "Name": "In my Dream",
      "Cmps": "ND Lee"
    },
    {
      "Index": 251,
      "Ctgr": "BS",
      "Name": "Lover (BS Style)",
      "Cmps": "ND Lee"
    },
    {
      "Index": 252,
      "Ctgr": "CE",
      "Name": "Lover (CE Style)",
      "Cmps": "ND Lee"
    },
    {
      "Index": 253,
      "Ctgr": "P1",
      "Name": "Never Say",
      "Cmps": "ND Lee"
    },
    {
      "Index": 254,
      "Ctgr": "P1",
      "Name": "ON",
      "Cmps": "ND Lee"
    },
    {
      "Index": 255,
      "Ctgr": "P1",
      "Name": "REVENGE",
      "Cmps": "ND Lee"
    },
    {
      "Index": 256,
      "Ctgr": "P2",
      "Name": "STALKER",
      "Cmps": "ND Lee"
    },
    {
      "Index": 257,
      "Ctgr": "BS",
      "Name": "Y (BS Style)",
      "Cmps": "ND Lee"
    },
    {
      "Index": 258,
      "Ctgr": "CE",
      "Name": "Y (CE Style)",
      "Cmps": "ND Lee"
    },
    {
      "Index": 259,
      "Ctgr": "T2",
      "Name": "Y ~Extended Mix~",
      "Cmps": "ND Lee"
    },
    {
      "Index": 260,
      "Ctgr": "ES",
      "Name": "Yo! Max!",
      "Cmps": "ND Lee"
    },
    {
      "Index": 261,
      "Ctgr": "P2",
      "Name": "설레임",
      "Cmps": "ND Lee"
    },
    {
      "Index": 262,
      "Ctgr": "T3",
      "Name": "설레임 Part.2",
      "Cmps": "ND Lee"
    },
    {
      "Index": 263,
      "Ctgr": "P1",
      "Name": "아침형 인간",
      "Cmps": "ND Lee"
    },
    {
      "Index": 264,
      "Ctgr": "RE",
      "Name": "Armored Phantom",
      "Cmps": "ned"
    },
    {
      "Index": 265,
      "Ctgr": "RE",
      "Name": "Shadow Flower",
      "Cmps": "ned"
    },
    {
      "Index": 266,
      "Ctgr": "CY",
      "Name": "CODE NAME ： ZERO",
      "Cmps": "NeLiME"
    },
    {
      "Index": 267,
      "Ctgr": "RE",
      "Name": "The Lost Story",
      "Cmps": "NEOWIZ Bless Soundteam"
    },
    {
      "Index": 268,
      "Ctgr": "P1",
      "Name": "Chrono Breakers",
      "Cmps": "NieN"
    },
    {
      "Index": 269,
      "Ctgr": "T3",
      "Name": "Feel Ma Beat",
      "Cmps": "NieN"
    },
    {
      "Index": 270,
      "Ctgr": "P2",
      "Name": "For the IKARUS",
      "Cmps": "NieN"
    },
    {
      "Index": 271,
      "Ctgr": "P2",
      "Name": "Hello Pinky",
      "Cmps": "NieN"
    },
    {
      "Index": 272,
      "Ctgr": "P3",
      "Name": "Leave me alone",
      "Cmps": "NieN"
    },
    {
      "Index": 273,
      "Ctgr": "P3",
      "Name": "Mellow D Fantasy",
      "Cmps": "NieN"
    },
    {
      "Index": 274,
      "Ctgr": "P2",
      "Name": "Midnight Blood",
      "Cmps": "NieN"
    },
    {
      "Index": 275,
      "Ctgr": "TR",
      "Name": "Mind Control",
      "Cmps": "NieN"
    },
    {
      "Index": 276,
      "Ctgr": "TR",
      "Name": "NB Girls",
      "Cmps": "NieN"
    },
    {
      "Index": 277,
      "Ctgr": "P2",
      "Name": "NB POWER",
      "Cmps": "NieN"
    },
    {
      "Index": 278,
      "Ctgr": "RE",
      "Name": "NB RANGER - Virgin Force",
      "Cmps": "NieN"
    },
    {
      "Index": 279,
      "Ctgr": "P2",
      "Name": "NB Rangers -Returns-",
      "Cmps": "NieN"
    },
    {
      "Index": 280,
      "Ctgr": "P1",
      "Name": "OBLIVION ~Rockin' Night Style~",
      "Cmps": "NieN"
    },
    {
      "Index": 281,
      "Ctgr": "RE",
      "Name": "Only for you",
      "Cmps": "NieN"
    },
    {
      "Index": 282,
      "Ctgr": "T2",
      "Name": "Rage Of Demon",
      "Cmps": "NieN"
    },
    {
      "Index": 283,
      "Ctgr": "ES",
      "Name": "Real Over Drive",
      "Cmps": "NieN"
    },
    {
      "Index": 284,
      "Ctgr": "RE",
      "Name": "Remains Of Doom",
      "Cmps": "NieN"
    },
    {
      "Index": 285,
      "Ctgr": "VE",
      "Name": "Remember Me",
      "Cmps": "NieN"
    },
    {
      "Index": 286,
      "Ctgr": "P1",
      "Name": "Road Of Death",
      "Cmps": "NieN"
    },
    {
      "Index": 287,
      "Ctgr": "P1",
      "Name": "Rock Or Die",
      "Cmps": "NieN"
    },
    {
      "Index": 288,
      "Ctgr": "P2",
      "Name": "Rolling On the Duck",
      "Cmps": "NieN"
    },
    {
      "Index": 289,
      "Ctgr": "TR",
      "Name": "Someday",
      "Cmps": "NieN"
    },
    {
      "Index": 290,
      "Ctgr": "T2",
      "Name": "Trip",
      "Cmps": "NieN"
    },
    {
      "Index": 291,
      "Ctgr": "T3",
      "Name": "You & Me",
      "Cmps": "NieN"
    },
    {
      "Index": 292,
      "Ctgr": "BS",
      "Name": "Fever Pitch Girl",
      "Cmps": "Nikacha"
    },
    {
      "Index": 293,
      "Ctgr": "VE",
      "Name": "Lisrim",
      "Cmps": "onoken"
    },
    {
      "Index": 294,
      "Ctgr": "CY",
      "Name": "Ververg",
      "Cmps": "onoken"
    },
    {
      "Index": 295,
      "Ctgr": "RE",
      "Name": "NEON 1989 (ESTi Remix)",
      "Cmps": "OREO"
    },
    {
      "Index": 296,
      "Ctgr": "T1",
      "Name": "Dear my Lady",
      "Cmps": "Oriental ST8"
    },
    {
      "Index": 297,
      "Ctgr": "T1",
      "Name": "Shoreline",
      "Cmps": "Oriental ST8"
    },
    {
      "Index": 298,
      "Ctgr": "P2",
      "Name": "SQUEEZE",
      "Cmps": "Oriental ST8"
    },
    {
      "Index": 299,
      "Ctgr": "P3",
      "Name": "Desperado ~Nu Skool Mix~",
      "Cmps": "Paul Bazooka"
    },
    {
      "Index": 300,
      "Ctgr": "RE",
      "Name": "Don't Die",
      "Cmps": "Paul Bazooka"
    },
    {
      "Index": 301,
      "Ctgr": "P3",
      "Name": "Enemy Storm ~Dark Jungle Mix~",
      "Cmps": "Paul Bazooka"
    },
    {
      "Index": 302,
      "Ctgr": "RE",
      "Name": "Kung Brother",
      "Cmps": "Paul Bazooka"
    },
    {
      "Index": 303,
      "Ctgr": "P3",
      "Name": "Luv Flow ~Funky House Mix~",
      "Cmps": "Paul Bazooka"
    },
    {
      "Index": 304,
      "Ctgr": "P3",
      "Name": "MASAI ~Electro House Mix~",
      "Cmps": "Paul Bazooka"
    },
    {
      "Index": 305,
      "Ctgr": "P3",
      "Name": "NB Ranger ： Nonstop Remix",
      "Cmps": "Paul Bazooka"
    },
    {
      "Index": 306,
      "Ctgr": "VE",
      "Name": "Never Die",
      "Cmps": "Paul Bazooka"
    },
    {
      "Index": 307,
      "Ctgr": "RE",
      "Name": "Nevermind",
      "Cmps": "Paul Bazooka"
    },
    {
      "Index": 308,
      "Ctgr": "T3",
      "Name": "SigNalize",
      "Cmps": "Paul Bazooka"
    },
    {
      "Index": 309,
      "Ctgr": "TR",
      "Name": "The One",
      "Cmps": "Paul Bazooka"
    },
    {
      "Index": 310,
      "Ctgr": "P3",
      "Name": "The Rain Maker",
      "Cmps": "Paul Bazooka"
    },
    {
      "Index": 311,
      "Ctgr": "RE",
      "Name": "We're All Gonna Die",
      "Cmps": "Paul Bazooka"
    },
    {
      "Index": 312,
      "Ctgr": "RE",
      "Name": "Kingdom",
      "Cmps": "Phantom sage"
    },
    {
      "Index": 313,
      "Ctgr": "P2",
      "Name": "Brandnew Days",
      "Cmps": "PlanetBoom"
    },
    {
      "Index": 314,
      "Ctgr": "TR",
      "Name": "For Seasons ~Air Guitar Mix~",
      "Cmps": "PlanetBoom"
    },
    {
      "Index": 315,
      "Ctgr": "P2",
      "Name": "Get on Top",
      "Cmps": "PlanetBoom"
    },
    {
      "Index": 316,
      "Ctgr": "BS",
      "Name": "Keys to the World",
      "Cmps": "PlanetBoom"
    },
    {
      "Index": 317,
      "Ctgr": "BS",
      "Name": "Lovely hands",
      "Cmps": "PlanetBoom"
    },
    {
      "Index": 318,
      "Ctgr": "T2",
      "Name": "MonoXide",
      "Cmps": "PlanetBoom"
    },
    {
      "Index": 319,
      "Ctgr": "P3",
      "Name": "Raise me up",
      "Cmps": "PlanetBoom"
    },
    {
      "Index": 320,
      "Ctgr": "P2",
      "Name": "StarFish",
      "Cmps": "PlanetBoom"
    },
    {
      "Index": 321,
      "Ctgr": "T1",
      "Name": "SuperSonic",
      "Cmps": "PlanetBoom"
    },
    {
      "Index": 322,
      "Ctgr": "T3",
      "Name": "Supersonic 2011",
      "Cmps": "PlanetBoom / Sound LAB"
    },
    {
      "Index": 323,
      "Ctgr": "RE",
      "Name": "Sad Machine",
      "Cmps": "Porter Robinson"
    },
    {
      "Index": 324,
      "Ctgr": "VE",
      "Name": "welcome to the space (feat. Jisun)",
      "Cmps": "Pory"
    },
    {
      "Index": 325,
      "Ctgr": "T2",
      "Name": "Burn it Down",
      "Cmps": "Psycho-Remi"
    },
    {
      "Index": 326,
      "Ctgr": "T2",
      "Name": "The Guilty",
      "Cmps": "Psycho-Remi"
    },
    {
      "Index": 327,
      "Ctgr": "VE",
      "Name": "Kensei",
      "Cmps": "Pure 100%"
    },
    {
      "Index": 328,
      "Ctgr": "DM",
      "Name": "Dream",
      "Cmps": "Rabpit"
    },
    {
      "Index": 329,
      "Ctgr": "RE",
      "Name": "So Happy",
      "Cmps": "Raven & Kreyn"
    },
    {
      "Index": 330,
      "Ctgr": "GC",
      "Name": "OVER THE NIGHT",
      "Cmps": "REDALiCE"
    },
    {
      "Index": 331,
      "Ctgr": "T2",
      "Name": "Airwave",
      "Cmps": "ReX"
    },
    {
      "Index": 332,
      "Ctgr": "BS",
      "Name": "Airwave ~Extended Mix~",
      "Cmps": "ReX"
    },
    {
      "Index": 333,
      "Ctgr": "BS",
      "Name": "Heart of Witch",
      "Cmps": "ReX"
    },
    {
      "Index": 334,
      "Ctgr": "CE",
      "Name": "고백, 꽃, 늑대",
      "Cmps": "ReX"
    },
    {
      "Index": 335,
      "Ctgr": "BS",
      "Name": "고백, 꽃, 늑대 part.2",
      "Cmps": "ReX"
    },
    {
      "Index": 336,
      "Ctgr": "GF",
      "Name": "Barbarous Funera",
      "Cmps": "Rikako Watanabe (Basicape)"
    },
    {
      "Index": 337,
      "Ctgr": "P2",
      "Name": "Good Bye",
      "Cmps": "Ruby Tuesday"
    },
    {
      "Index": 338,
      "Ctgr": "CE",
      "Name": "Here in the Moment",
      "Cmps": "Ruby Tuesday"
    },
    {
      "Index": 339,
      "Ctgr": "CE",
      "Name": "Here in the Moment ~Extended Mix~",
      "Cmps": "Ruby Tuesday"
    },
    {
      "Index": 340,
      "Ctgr": "BS",
      "Name": "Ready Now",
      "Cmps": "Ruby Tuesday"
    },
    {
      "Index": 341,
      "Ctgr": "P2",
      "Name": "Showtime",
      "Cmps": "Ruby Tuesday"
    },
    {
      "Index": 342,
      "Ctgr": "P2",
      "Name": "Stay with me",
      "Cmps": "Ruby Tuesday"
    },
    {
      "Index": 343,
      "Ctgr": "P2",
      "Name": "Your Own Miracle",
      "Cmps": "Ruby Tuesday"
    },
    {
      "Index": 344,
      "Ctgr": "CH",
      "Name": "Trrricksters!!",
      "Cmps": "s-don vs. Hino Isuka"
    },
    {
      "Index": 345,
      "Ctgr": "P1",
      "Name": "Temptation",
      "Cmps": "S-TRO"
    },
    {
      "Index": 346,
      "Ctgr": "CY",
      "Name": "AXION",
      "Cmps": "sakuzyo"
    },
    {
      "Index": 347,
      "Ctgr": "CH",
      "Name": "Cyberozar",
      "Cmps": "sakuzyo"
    },
    {
      "Index": 348,
      "Ctgr": "T3",
      "Name": "Bamboo on Bamboo",
      "Cmps": "Sampling Masters MEGA"
    },
    {
      "Index": 349,
      "Ctgr": "RE",
      "Name": "Mulch",
      "Cmps": "Sampling Masters MEGA"
    },
    {
      "Index": 350,
      "Ctgr": "CH",
      "Name": "The wheel to the right",
      "Cmps": "Sampling Masters MEGA"
    },
    {
      "Index": 351,
      "Ctgr": "RE",
      "Name": "ALiCE",
      "Cmps": "seibin"
    },
    {
      "Index": 352,
      "Ctgr": "DM",
      "Name": "Sairai",
      "Cmps": "Shinichi Kobayashi"
    },
    {
      "Index": 353,
      "Ctgr": "CY",
      "Name": "EMber",
      "Cmps": "SIHanatsuka"
    },
    {
      "Index": 354,
      "Ctgr": "VE",
      "Name": "Fancy Night",
      "Cmps": "SiNA × CHUCK"
    },
    {
      "Index": 355,
      "Ctgr": "T1",
      "Name": "Access",
      "Cmps": "Sphazer"
    },
    {
      "Index": 356,
      "Ctgr": "T1",
      "Name": "Area 7",
      "Cmps": "Sphazer"
    },
    {
      "Index": 357,
      "Ctgr": "RE",
      "Name": "Tok! Tok! Tok!",
      "Cmps": "STARTRACK"
    },
    {
      "Index": 358,
      "Ctgr": "CE",
      "Name": "Fate",
      "Cmps": "STi"
    },
    {
      "Index": 359,
      "Ctgr": "T3",
      "Name": "유령",
      "Cmps": "STi"
    },
    {
      "Index": 360,
      "Ctgr": "CE",
      "Name": "DARK ENVY",
      "Cmps": "Sugardonut"
    },
    {
      "Index": 361,
      "Ctgr": "T1",
      "Name": "Fury",
      "Cmps": "Sugardonut"
    },
    {
      "Index": 362,
      "Ctgr": "T3",
      "Name": "Now a NEW Day",
      "Cmps": "Sui.Jay"
    },
    {
      "Index": 363,
      "Ctgr": "P1",
      "Name": "FEAR",
      "Cmps": "Supbaby"
    },
    {
      "Index": 364,
      "Ctgr": "P1",
      "Name": "FTR",
      "Cmps": "Supbaby"
    },
    {
      "Index": 365,
      "Ctgr": "P2",
      "Name": "Higher",
      "Cmps": "Supbaby"
    },
    {
      "Index": 366,
      "Ctgr": "RE",
      "Name": "The Feelings",
      "Cmps": "Supbaby"
    },
    {
      "Index": 367,
      "Ctgr": "BS",
      "Name": "Secret World",
      "Cmps": "Sweetune"
    },
    {
      "Index": 368,
      "Ctgr": "CE",
      "Name": "너에게",
      "Cmps": "Sweetune"
    },
    {
      "Index": 369,
      "Ctgr": "DM",
      "Name": "Legacy",
      "Cmps": "switchworks"
    },
    {
      "Index": 370,
      "Ctgr": "CH",
      "Name": "Garakuta Doll Play",
      "Cmps": "t+pazolite"
    },
    {
      "Index": 371,
      "Ctgr": "GC",
      "Name": "Good Night, Bad Luck.",
      "Cmps": "t+pazolite"
    },
    {
      "Index": 372,
      "Ctgr": "GC",
      "Name": "Marry me, Nightmare",
      "Cmps": "t+pazolite"
    },
    {
      "Index": 373,
      "Ctgr": "GC",
      "Name": "Satisfiction",
      "Cmps": "t+pazolite"
    },
    {
      "Index": 374,
      "Ctgr": "T3",
      "Name": "Black Swan",
      "Cmps": "TAK"
    },
    {
      "Index": 375,
      "Ctgr": "EM",
      "Name": "안아줘",
      "Cmps": "TAK / seibin"
    },
    {
      "Index": 376,
      "Ctgr": "CH",
      "Name": "Ikazuchi",
      "Cmps": "Takenobu Mitsuyoshi"
    },
    {
      "Index": 377,
      "Ctgr": "T3",
      "Name": "Right Back",
      "Cmps": "TANUKI"
    },
    {
      "Index": 378,
      "Ctgr": "CY",
      "Name": "Mammal",
      "Cmps": "Teikyou"
    },
    {
      "Index": 379,
      "Ctgr": "BS",
      "Name": "PDM",
      "Cmps": "Trish"
    },
    {
      "Index": 380,
      "Ctgr": "RE",
      "Name": "Binary World",
      "Cmps": "Tsukasa"
    },
    {
      "Index": 381,
      "Ctgr": "P2",
      "Name": "Chain of Gravity",
      "Cmps": "Tsukasa"
    },
    {
      "Index": 382,
      "Ctgr": "BS",
      "Name": "Colours of Sorrow",
      "Cmps": "Tsukasa"
    },
    {
      "Index": 383,
      "Ctgr": "T3",
      "Name": "Dark Prism",
      "Cmps": "Tsukasa"
    },
    {
      "Index": 384,
      "Ctgr": "BS",
      "Name": "Grave Consequence",
      "Cmps": "Tsukasa"
    },
    {
      "Index": 385,
      "Ctgr": "RE",
      "Name": "Grid System",
      "Cmps": "Tsukasa"
    },
    {
      "Index": 386,
      "Ctgr": "CE",
      "Name": "In My Heart",
      "Cmps": "Tsukasa"
    },
    {
      "Index": 387,
      "Ctgr": "T1",
      "Name": "Landscape",
      "Cmps": "Tsukasa"
    },
    {
      "Index": 388,
      "Ctgr": "T3",
      "Name": "Over the Rainbow",
      "Cmps": "Tsukasa"
    },
    {
      "Index": 389,
      "Ctgr": "CY",
      "Name": "Shoot out",
      "Cmps": "Tsukasa"
    },
    {
      "Index": 390,
      "Ctgr": "CE",
      "Name": "The Clear Blue Sky",
      "Cmps": "Tsukasa"
    },
    {
      "Index": 391,
      "Ctgr": "GC",
      "Name": "HB-axeleration",
      "Cmps": "Tsukasa Yatoki"
    },
    {
      "Index": 392,
      "Ctgr": "T1",
      "Name": "Play the Future",
      "Cmps": "Urbatronic Chopsticks"
    },
    {
      "Index": 393,
      "Ctgr": "T1",
      "Name": "The Last Dance",
      "Cmps": "Urbatronic Chopsticks"
    },
    {
      "Index": 394,
      "Ctgr": "P3",
      "Name": "IF",
      "Cmps": "Vanilla Unity"
    },
    {
      "Index": 395,
      "Ctgr": "RE",
      "Name": "Ghost Voices",
      "Cmps": "Virtual Self"
    },
    {
      "Index": 396,
      "Ctgr": "P1",
      "Name": "피아노 협주곡 1번",
      "Cmps": "Wav Factory"
    },
    {
      "Index": 397,
      "Ctgr": "RE",
      "Name": "Chemical Slave",
      "Cmps": "XeoN"
    },
    {
      "Index": 398,
      "Ctgr": "T2",
      "Name": "Dream of Winds",
      "Cmps": "XeoN"
    },
    {
      "Index": 399,
      "Ctgr": "T2",
      "Name": "Eternal Fantasy ~유니의 꿈~",
      "Cmps": "XeoN"
    },
    {
      "Index": 400,
      "Ctgr": "RE",
      "Name": "Fly Away",
      "Cmps": "XeoN"
    },
    {
      "Index": 401,
      "Ctgr": "T1",
      "Name": "Thor",
      "Cmps": "XeoN"
    },
    {
      "Index": 402,
      "Ctgr": "T2",
      "Name": "Thor ~Extended Mix~",
      "Cmps": "XeoN"
    },
    {
      "Index": 403,
      "Ctgr": "RE",
      "Name": "Watch Your Step",
      "Cmps": "XeoN"
    },
    {
      "Index": 404,
      "Ctgr": "T3",
      "Name": "Xeus",
      "Cmps": "XeoN"
    },
    {
      "Index": 405,
      "Ctgr": "DM",
      "Name": "ANiMA",
      "Cmps": "xi"
    },
    {
      "Index": 406,
      "Ctgr": "P2",
      "Name": "Cherokee",
      "Cmps": "xxdbxx"
    },
    {
      "Index": 407,
      "Ctgr": "P1",
      "Name": "Fever GJ",
      "Cmps": "xxdbxx"
    },
    {
      "Index": 408,
      "Ctgr": "P1",
      "Name": "Jupiter Driving",
      "Cmps": "xxdbxx"
    },
    {
      "Index": 409,
      "Ctgr": "P1",
      "Name": "Light House",
      "Cmps": "xxdbxx"
    },
    {
      "Index": 410,
      "Ctgr": "P1",
      "Name": "One the Love",
      "Cmps": "xxdbxx"
    },
    {
      "Index": 411,
      "Ctgr": "RE",
      "Name": "Over Your Dream",
      "Cmps": "xxdbxx"
    },
    {
      "Index": 412,
      "Ctgr": "TR",
      "Name": "Talk! Talk!",
      "Cmps": "xxdbxx"
    },
    {
      "Index": 413,
      "Ctgr": "P2",
      "Name": "태권부리",
      "Cmps": "xxdbxx"
    },
    {
      "Index": 414,
      "Ctgr": "RE",
      "Name": "Always",
      "Cmps": "YUGI / Mool"
    },
    {
      "Index": 415,
      "Ctgr": "DM",
      "Name": "Undo",
      "Cmps": "Yuk-cheung Chun"
    },
    {
      "Index": 416,
      "Ctgr": "RE",
      "Name": "Liar",
      "Cmps": "zts"
    },
    {
      "Index": 417,
      "Ctgr": "P2",
      "Name": "plastic method",
      "Cmps": "zts"
    },
    {
      "Index": 418,
      "Ctgr": "P2",
      "Name": "WhiteBlue",
      "Cmps": "zts"
    },
    {
      "Index": 419,
      "Ctgr": "CE",
      "Name": "Tell Me",
      "Cmps": "이궐"
    },
    {
      "Index": 420,
      "Ctgr": "RE",
      "Name": "Relation Again (ESTi's Remix)",
      "Cmps": "Tsukasa / ESTi"
    },
    {
      "Index": 421,
      "Ctgr": "NX",
      "Name": "공성전 ~Pierre Blanche, Yonce Remix~",
      "Cmps": "Pierre Blanche, Yonce"
    },
    {
      "Index": 422,
      "Ctgr": "NX",
      "Name": "광명의 루 ： 루 라바다",
      "Cmps": "Studio EIM"
    },
    {
      "Index": 423,
      "Ctgr": "NX",
      "Name": "부여성 ~Blosso Remix~",
      "Cmps": "Blooso"
    },
    {
      "Index": 424,
      "Ctgr": "NX",
      "Name": "소년 모험가 ~SiNA Remix~",
      "Cmps": "SiNA"
    },
    {
      "Index": 425,
      "Ctgr": "NX",
      "Name": "어릴적 할머니가 들려주신 옛 전설",
      "Cmps": "HanStone"
    },
    {
      "Index": 426,
      "Ctgr": "NX",
      "Name": "연합군과 제국군",
      "Cmps": "NEXON"
    },
    {
      "Index": 427,
      "Ctgr": "NX",
      "Name": "전설이 시작된 곳 ~VoidRover Remix~",
      "Cmps": "VoidRover"
    },
    {
      "Index": 428,
      "Ctgr": "NX",
      "Name": "죽음의 신 ： 크로우 크루아흐",
      "Cmps": "Studio EIM"
    },
    {
      "Index": 429,
      "Ctgr": "NX",
      "Name": "최종무곡",
      "Cmps": "HanStone"
    },
    {
      "Index": 430,
      "Ctgr": "NX",
      "Name": "카트라이더 Mashup ~Cosmograph Remix~",
      "Cmps": "Cosmograph"
    },
    {
      "Index": 431,
      "Ctgr": "NX",
      "Name": "카트라이더 Mashup ~Pure 100％ Remix~",
      "Cmps": "Pure 100%"
    },
    {
      "Index": 432,
      "Ctgr": "NX",
      "Name": "카트라이더, 크레이지아케이드, 버블파이터 Main theme ~CHUCK Remix~",
      "Cmps": "CHUCK"
    },
    {
      "Index": 433,
      "Ctgr": "NX",
      "Name": "Apparition",
      "Cmps": "ESTi"
    },
    {
      "Index": 434,
      "Ctgr": "NX",
      "Name": "Constant Moderato",
      "Cmps": "Mitsukiyo"
    },
    {
      "Index": 435,
      "Ctgr": "NX",
      "Name": "It's my war now",
      "Cmps": "김동현"
    },
    {
      "Index": 436,
      "Ctgr": "NX",
      "Name": "Lacheln, The City of Dreams",
      "Cmps": "NEXON"
    },
    {
      "Index": 437,
      "Ctgr": "NX",
      "Name": "Reminiscence",
      "Cmps": "Nauts"
    },
    {
      "Index": 438,
      "Ctgr": "NX",
      "Name": "Start The Adventure ~SOPHI Remix~",
      "Cmps": "SOPHI"
    },
    {
      "Index": 439,
      "Ctgr": "NX",
      "Name": "Tayberrs - Collapsed Paradise",
      "Cmps": "정영걸"
    },
    {
      "Index": 440,
      "Ctgr": "NX",
      "Name": "The Little Adventurer",
      "Cmps": "Studio EIM"
    },
    {
      "Index": 441,
      "Ctgr": "NX",
      "Name": "The Raindrop Flower ~jam-jam Remix~",
      "Cmps": "jam-jam"
    }
  ]
}